{
  "name": "Synthetic Tent",
  "permission": {
    "default": 0,
    "qtb8j5Fh7Hu0wRrz": 3
  },
  "type": "equipment",
  "data": {
    "description": {
      "value": "<p>@Compendium[compendiums-mix-dnd5e.um5-rules.R1ew21i3luHJHfV5]{UM5 Ch.6: Gear} @Compendium[compendiums-mix-dnd5e.um5-rules.oW9iuEoxWvtPKvDo]{UM5 Ch.6: Tech Level 0-5}</p>\n<p>Tents come in two, four, and six person capacities.&nbsp;Most tents utilize flexible poles and are available in&nbsp;dome, tunnel, single-hoop, and geodesic styles. It takes&nbsp;5 minutes to set up and take down properly.</p>",
      "chat": "",
      "unidentified": ""
    },
    "source": "UM5 p.97",
    "quantity": 1,
    "weight": 0,
    "price": 0,
    "attuned": false,
    "equipped": false,
    "rarity": "",
    "identified": true,
    "activation": {
      "type": "",
      "cost": 0,
      "condition": ""
    },
    "duration": {
      "value": null,
      "units": ""
    },
    "target": {
      "value": null,
      "units": "",
      "type": ""
    },
    "range": {
      "value": null,
      "long": null,
      "units": ""
    },
    "uses": {
      "value": 0,
      "max": 0,
      "per": null
    },
    "consume": {
      "type": "",
      "target": null,
      "amount": null
    },
    "ability": null,
    "actionType": "",
    "attackBonus": 0,
    "chatFlavor": "",
    "critical": null,
    "damage": {
      "parts": [],
      "versatile": ""
    },
    "formula": "",
    "save": {
      "ability": "",
      "dc": null,
      "scaling": "spell"
    },
    "armor": {
      "value": 0,
      "type": "",
      "dex": null
    },
    "hp": {
      "value": 0,
      "max": 0,
      "dt": null,
      "conditions": ""
    },
    "speed": {
      "value": null,
      "conditions": ""
    },
    "strength": 0,
    "stealth": false,
    "proficient": false
  },
  "flags": {
    "betterRolls5e": {
      "critRange": {
        "type": "String",
        "value": ""
      },
      "critDamage": {
        "type": "String",
        "value": ""
      },
      "quickDesc": {
        "type": "Boolean",
        "value": true,
        "altValue": true
      },
      "quickAttack": {
        "type": "Boolean",
        "value": true,
        "altValue": true
      },
      "quickSave": {
        "type": "Boolean",
        "value": true,
        "altValue": true
      },
      "quickDamage": {
        "type": "Array",
        "value": [],
        "altValue": [],
        "context": []
      },
      "quickProperties": {
        "type": "Boolean",
        "value": true,
        "altValue": true
      },
      "quickCharges": {
        "type": "Boolean",
        "value": true,
        "altValue": true
      },
      "quickOther": {
        "type": "Boolean",
        "value": true,
        "altValue": true,
        "context": ""
      },
      "quickFlavor": {
        "type": "Boolean",
        "value": true,
        "altValue": true
      }
    }
  },
  "img": "systems/dnd5e/icons/items/inventory/cloth-green.jpg",
  "_id": "HHgvj3YyUtbmrrXC",
  "effects": [],
  "_key": "!items!HHgvj3YyUtbmrrXC"
}
